vbnigmm/__init__.py
vbnigmm/backend/__init__.py
vbnigmm/backend/bessel.py
vbnigmm/backend/constant.py
vbnigmm/backend/current.py
vbnigmm/backend/gamma.py
vbnigmm/backend/search.py
vbnigmm/backend/tensorflow/__init__.py
vbnigmm/backend/tensorflow/keras.py
vbnigmm/backend/tensorflow/ops.py
vbnigmm/backend/tensorflow/ufunc.py
vbnigmm/backend/tri.py
vbnigmm/distributions/__init__.py
vbnigmm/distributions/base.py
vbnigmm/distributions/dirichlet.py
vbnigmm/distributions/gamma.py
vbnigmm/distributions/gauss.py
vbnigmm/distributions/invgauss.py
vbnigmm/distributions/wishart.py
vbnigmm/linalg/__init__.py
vbnigmm/linalg/base.py
vbnigmm/linalg/matrix.py
vbnigmm/linalg/scalar.py
vbnigmm/linalg/vector.py
vbnigmm/mixture/__init__.py
vbnigmm/mixture/base.py
vbnigmm/mixture/dpm.py
vbnigmm/mixture/gmm.py
vbnigmm/mixture/nigmm.py
vbnigmm/mixture/nigmm_params.py
vbnigmm/mixture/utils.py
vbnigmm-2.4.1.dist-info/LICENSE
vbnigmm-2.4.1.dist-info/WHEEL
vbnigmm-2.4.1.dist-info/METADATA
vbnigmm-2.4.1.dist-info/RECORD
