Metadata-Version: 2.1
Name: vbnigmm
Version: 2.4.1
Summary: Variational Bayes algorithm for normal inverse Gaussian mixture models
Home-page: https://github.com/tk2lab/vbnigmm
License: GPL-3.0-only
Keywords: clustering
Author: TAKEKAWA Takashi
Author-email: takekawa@tk2lab.org
Requires-Python: >=3.7,<4.0
Classifier: License :: OSI Approved :: GNU General Public License v3 (GPLv3)
Classifier: Programming Language :: Python :: 3
Classifier: Programming Language :: Python :: 3.7
Classifier: Programming Language :: Python :: 3.8
Classifier: Programming Language :: Python :: 3.9
Requires-Dist: tensorflow (>=2.4,<3.0)
Project-URL: Repository, https://github.com/tk2lab/vbnigmm
